[{"id":"133ba1ba.a0d1be","type":"tab","label":"withPython","disabled":false,"info":""},{"id":"c48e06ca.853d48","type":"tab","label":"withAutoAI","disabled":false,"info":""},{"id":"6600f3e4.ab446c","type":"ui_base","z":0,"theme":{"name":"theme-light","lightTheme":{"default":"#0094CE","baseColor":"#0094CE","baseFont":"-apple-system,BlinkMacSystemFont,Segoe UI,Roboto,Oxygen-Sans,Ubuntu,Cantarell,Helvetica Neue,sans-serif","edited":true,"reset":false},"darkTheme":{"default":"#097479","baseColor":"#097479","baseFont":"-apple-system,BlinkMacSystemFont,Segoe UI,Roboto,Oxygen-Sans,Ubuntu,Cantarell,Helvetica Neue,sans-serif","edited":false},"customTheme":{"name":"Untitled Theme 1","default":"#4B7930","baseColor":"#4B7930","baseFont":"-apple-system,BlinkMacSystemFont,Segoe UI,Roboto,Oxygen-Sans,Ubuntu,Cantarell,Helvetica Neue,sans-serif"},"themeState":{"base-color":{"default":"#0094CE","value":"#0094CE","edited":false},"page-titlebar-backgroundColor":{"value":"#0094CE","edited":false},"page-backgroundColor":{"value":"#fafafa","edited":false},"page-sidebar-backgroundColor":{"value":"#ffffff","edited":false},"group-textColor":{"value":"#1bbfff","edited":false},"group-borderColor":{"value":"#ffffff","edited":false},"group-backgroundColor":{"value":"#ffffff","edited":false},"widget-textColor":{"value":"#111111","edited":false},"widget-backgroundColor":{"value":"#0094ce","edited":false},"widget-borderColor":{"value":"#ffffff","edited":false},"base-font":{"value":"-apple-system,BlinkMacSystemFont,Segoe UI,Roboto,Oxygen-Sans,Ubuntu,Cantarell,Helvetica Neue,sans-serif"}},"angularTheme":{"primary":"indigo","accents":"blue","warn":"red","background":"grey"}},"site":{"name":"Node-RED Dashboard","hideToolbar":"false","allowSwipe":"false","lockMenu":"false","allowTempTheme":"true","dateFormat":"DD/MM/YYYY","sizes":{"sx":48,"sy":48,"gx":6,"gy":6,"cx":6,"cy":6,"px":0,"py":0}}},{"id":"2c87dd77.7be992","type":"ui_tab","z":0,"name":"Life Expectancy With Python ","icon":"dashboard","disabled":false,"hidden":false},{"id":"d34dd9fb.593098","type":"ui_tab","z":0,"name":"Life Expectancy Prediction without Python using AutoAI","icon":"dashboard","disabled":false,"hidden":false},{"id":"b88fc60e.7fdd08","type":"ui_group","z":0,"name":"Default","tab":"2c87dd77.7be992","order":1,"disp":true,"width":"6","collapse":false},{"id":"1dfb4dc1.e08162","type":"ui_group","z":0,"name":"Default","tab":"d34dd9fb.593098","order":1,"disp":true,"width":"6","collapse":false},{"id":"244a7f73.e2935","type":"ui_tab","z":"","name":"Home","icon":"dashboard","disabled":false,"hidden":false},{"id":"b1301e94.cb564","type":"ui_group","z":"","name":"Default","tab":"244a7f73.e2935","order":1,"disp":true,"width":"6","collapse":false},{"id":"80e8474a.c248b8","type":"ui_tab","z":"","name":"Home","icon":"dashboard","disabled":false,"hidden":false},{"id":"21767766.2a3a38","type":"ui_group","z":"","name":"Default","tab":"80e8474a.c248b8","order":1,"disp":true,"width":"6","collapse":false},{"id":"30a8d4f4.9d281c","type":"ui_group","z":"","name":"prediction","tab":"6ea9d6fd.b31598","order":1,"disp":true,"width":"6","collapse":false},{"id":"6ea9d6fd.b31598","type":"ui_tab","z":"","name":"Prediction ","icon":"dashboard","disabled":false,"hidden":false},{"id":"ffa43a24.e68f98","type":"ui_tab","z":"","name":"Home","icon":"dashboard","disabled":false,"hidden":false},{"id":"84cf2064.d67e6","type":"ui_group","z":"","name":"Default","tab":"ffa43a24.e68f98","order":1,"disp":true,"width":"6","collapse":false},{"id":"806e09f6.89ee38","type":"ui_base","theme":{"name":"theme-light","lightTheme":{"default":"#0094CE","baseColor":"#0094CE","baseFont":"-apple-system,BlinkMacSystemFont,Segoe UI,Roboto,Oxygen-Sans,Ubuntu,Cantarell,Helvetica Neue,sans-serif","edited":true,"reset":false},"darkTheme":{"default":"#097479","baseColor":"#097479","baseFont":"-apple-system,BlinkMacSystemFont,Segoe UI,Roboto,Oxygen-Sans,Ubuntu,Cantarell,Helvetica Neue,sans-serif","edited":false},"customTheme":{"name":"Untitled Theme 1","default":"#4B7930","baseColor":"#4B7930","baseFont":"-apple-system,BlinkMacSystemFont,Segoe UI,Roboto,Oxygen-Sans,Ubuntu,Cantarell,Helvetica Neue,sans-serif"},"themeState":{"base-color":{"default":"#0094CE","value":"#0094CE","edited":false},"page-titlebar-backgroundColor":{"value":"#0094CE","edited":false},"page-backgroundColor":{"value":"#fafafa","edited":false},"page-sidebar-backgroundColor":{"value":"#ffffff","edited":false},"group-textColor":{"value":"#1bbfff","edited":false},"group-borderColor":{"value":"#ffffff","edited":false},"group-backgroundColor":{"value":"#ffffff","edited":false},"widget-textColor":{"value":"#111111","edited":false},"widget-backgroundColor":{"value":"#0094ce","edited":false},"widget-borderColor":{"value":"#ffffff","edited":false},"base-font":{"value":"-apple-system,BlinkMacSystemFont,Segoe UI,Roboto,Oxygen-Sans,Ubuntu,Cantarell,Helvetica Neue,sans-serif"}},"angularTheme":{"primary":"indigo","accents":"blue","warn":"red","background":"grey"}},"site":{"name":"Node-RED Dashboard","hideToolbar":"false","allowSwipe":"false","lockMenu":"false","allowTempTheme":"true","dateFormat":"DD/MM/YYYY","sizes":{"sx":48,"sy":48,"gx":6,"gy":6,"cx":6,"cy":6,"px":0,"py":0}}},{"id":"bcbbe35.c34962","type":"ui_group","z":"","name":"Default","tab":"cf38d001.2ae5e","order":1,"disp":true,"width":"6","collapse":false},{"id":"cf38d001.2ae5e","type":"ui_tab","z":"","name":"Life Expectancy Prediction without Python using AutoAI","icon":"dashboard","disabled":false,"hidden":false},{"id":"1fe3dc8.24e0824","type":"debug","z":"133ba1ba.a0d1be","name":"","active":true,"tosidebar":true,"console":false,"tostatus":false,"complete":"payload","targetType":"msg","x":490,"y":400,"wires":[]},{"id":"9a2f08b1.f9d278","type":"ui_form","z":"133ba1ba.a0d1be","name":"","label":"","group":"b88fc60e.7fdd08","order":0,"width":0,"height":0,"options":[{"label":"Country","value":"a","type":"text","required":true,"rows":null},{"label":"Year","value":"b","type":"number","required":true,"rows":null},{"label":"Status","value":"c","type":"text","required":true,"rows":null},{"label":"BMI","value":"d","type":"number","required":true,"rows":null},{"label":"Adult Mortality","value":"e","type":"number","required":true,"rows":null},{"label":"Infant Deaths","value":"f","type":"number","required":true,"rows":null},{"label":"Alcohol","value":"g","type":"number","required":true,"rows":null},{"label":"Percentage Expenditure","value":"h","type":"number","required":true,"rows":null},{"label":"HepatitisB","value":"i","type":"number","required":true,"rows":null},{"label":"Under five deaths","value":"u","type":"number","required":true,"rows":null},{"label":"Polio","value":"j","type":"number","required":true,"rows":null},{"label":"Total Expenditure","value":"k","type":"number","required":true,"rows":null},{"label":"Diphtheria","value":"l","type":"number","required":true,"rows":null},{"label":"HIV","value":"m","type":"number","required":true,"rows":null},{"label":"GDP","value":"n","type":"number","required":true,"rows":null},{"label":"Population","value":"o","type":"number","required":true,"rows":null},{"label":"Thinness 10 to 19 years","value":"p","type":"number","required":true,"rows":null},{"label":"Thinness 5 to 9 years","value":"q","type":"number","required":true,"rows":null},{"label":"Income composition of resourses","value":"r","type":"number","required":true,"rows":null},{"label":"Schooling","value":"s","type":"number","required":true,"rows":null},{"label":"Measles","value":"t","type":"number","required":true,"rows":null}],"formValue":{"a":"","b":"","c":"","d":"","e":"","f":"","g":"","h":"","i":"","u":"","j":"","k":"","l":"","m":"","n":"","o":"","p":"","q":"","r":"","s":"","t":""},"payload":"","submit":"Predict","cancel":"Cancel","topic":"","x":200,"y":200,"wires":[["8c075830.2039c8"]]},{"id":"8c075830.2039c8","type":"function","z":"133ba1ba.a0d1be","name":"pre token","func":"global.set(\"a\",msg.payload.a);\nglobal.set(\"b\",msg.payload.b);\nglobal.set(\"c\",msg.payload.c);\nglobal.set(\"d\",msg.payload.d);\nglobal.set(\"e\",msg.payload.e);\nglobal.set(\"f\",msg.payload.f);\nglobal.set(\"g\",msg.payload.g);\nglobal.set(\"h\",msg.payload.h);\nglobal.set(\"i\",msg.payload.i);\nglobal.set(\"u\",msg.payload.u);\nglobal.set(\"j\",msg.payload.j);\nglobal.set(\"k\",msg.payload.k);\nglobal.set(\"l\",msg.payload.l);\nglobal.set(\"m\",msg.payload.m);\nglobal.set(\"n\",msg.payload.n);\nglobal.set(\"o\",msg.payload.o);\nglobal.set(\"p\",msg.payload.p);\nglobal.set(\"q\",msg.payload.q);\nglobal.set(\"r\",msg.payload.r);\nglobal.set(\"s\",msg.payload.s);\nglobal.set(\"t\",msg.payload.t);\n\nvar apikey = \"YxYRBZZTnZuuF41FON3eWHTv2lFQfbEOgwLQ4N9rRK6d\";\nmsg.headers = {\"content-type\":\"application/x-www-form-urlencoded\"};\nmsg.payload = {\"grant_type\":\"urn:ibm:params:oauth:grant-type:apikey\",\"apikey\":apikey};\nreturn msg;","outputs":1,"noerr":0,"x":360,"y":200,"wires":[["49e5fac0.515c24"]]},{"id":"49e5fac0.515c24","type":"http request","z":"133ba1ba.a0d1be","name":"","method":"POST","ret":"obj","paytoqs":false,"url":"https://iam.cloud.ibm.com/identity/token","tls":"","persist":false,"proxy":"","authType":"","x":530,"y":200,"wires":[["f297e26e.f7ac5"]]},{"id":"f297e26e.f7ac5","type":"function","z":"133ba1ba.a0d1be","name":"post function","func":"var a = global.get(\"a\");\nvar b = global.get(\"b\");\nvar c = global.get(\"c\");\nvar d = global.get(\"d\");\nvar e = global.get(\"e\");\nvar f = global.get(\"f\");\nvar g = global.get(\"g\");\nvar h = global.get(\"h\");\nvar i = global.get(\"i\");\nvar u = global.get(\"u\");\nvar j = global.get(\"j\");\nvar k = global.get(\"k\");\nvar l = global.get(\"l\");\nvar m = global.get(\"m\");\nvar n = global.get(\"n\");\nvar o = global.get(\"o\");\nvar p = global.get(\"p\");\nvar q = global.get(\"q\");\nvar r = global.get(\"r\");\nvar s = global.get(\"s\");\nvar t = global.get(\"t\");\n\nvar token = msg.payload.access_token;\nvar instance_id = \"abea31c3-3ac1-467d-bfe6-a58059bf3209\";\nmsg.headers = {'Content-Type': 'application/json',\"Authorization\":\"Bearer\"+token, \"ML-Instance-ID\":instance_id}\n\nmsg.payload ={\"fields\":\n        ['Country', 'Year', 'Status', 'BMI', 'Adult_Mortality', 'Infant_Deaths',\n       'Alcohol', 'Percentage_Expenditure', 'Hepatitis_B', 'Under_Five_Deaths',\n       'Polio', 'Total_Expenditure', 'Diphtheria', 'HIV/AIDS', 'GDP',\n       'Population', 'Thinness_10_19_years', 'Thinness_5_9_years',\n       'Income_Composition_of_Resources', 'Schooling', 'Measles'],\n       \"values\": [[a,b,c,d,e,f,g,h,i,u,j,k,l,m,n,o,p,q,r,s,t]]};\nreturn msg;","outputs":1,"noerr":0,"x":710,"y":200,"wires":[["2c88ef30.c8cc"]]},{"id":"2c88ef30.c8cc","type":"http request","z":"133ba1ba.a0d1be","name":"","method":"POST","ret":"obj","paytoqs":false,"url":"https://eu-gb.ml.cloud.ibm.com/v3/wml_instances/abea31c3-3ac1-467d-bfe6-a58059bf3209/deployments/bbddad0e-e6c6-4c34-8b3c-1c89b9c1c866/online","tls":"","persist":false,"proxy":"","authType":"","x":250,"y":300,"wires":[["1fe3dc8.24e0824","8cc4a6a6.2ac518"]]},{"id":"8cc4a6a6.2ac518","type":"function","z":"133ba1ba.a0d1be","name":"final function","func":"msg.payload = msg.payload.values[0][0];\nreturn msg;","outputs":1,"noerr":0,"x":500,"y":300,"wires":[["afd2c01f.8de06"]]},{"id":"afd2c01f.8de06","type":"ui_text","z":"133ba1ba.a0d1be","group":"b88fc60e.7fdd08","order":1,"width":0,"height":0,"name":"","label":"Predictions","format":"{{msg.payload}}","layout":"row-spread","x":690,"y":300,"wires":[]},{"id":"d11a8c2c.01e61","type":"ui_form","z":"c48e06ca.853d48","name":"","label":"","group":"bcbbe35.c34962","order":1,"width":0,"height":0,"options":[{"label":"Country","value":"a","type":"text","required":true,"rows":null},{"label":"Year","value":"b","type":"number","required":true,"rows":null},{"label":"Status","value":"c","type":"text","required":true,"rows":null},{"label":"Adult Mortality","value":"d","type":"number","required":true,"rows":null},{"label":"Infant Deaths","value":"e","type":"number","required":true,"rows":null},{"label":"Alcohol","value":"f","type":"number","required":true,"rows":null},{"label":"Percentage Expenditure","value":"g","type":"number","required":true,"rows":null},{"label":"Hepatitis B","value":"h","type":"number","required":true,"rows":null},{"label":"Measles","value":"i","type":"number","required":true,"rows":null},{"label":"BMI","value":"j","type":"number","required":true,"rows":null},{"label":"Under five deaths","value":"k","type":"number","required":true,"rows":null},{"label":"Polio","value":"l","type":"number","required":true,"rows":null},{"label":"Total Expenditure","value":"m","type":"number","required":true,"rows":null},{"label":"Diphtheria","value":"n","type":"number","required":true,"rows":null},{"label":"HIV/AIDS","value":"o","type":"number","required":true,"rows":null},{"label":"GDP","value":"p","type":"number","required":true,"rows":null},{"label":"Population","value":"q","type":"number","required":true,"rows":null},{"label":"Thinness 1-19 years","value":"r","type":"number","required":true,"rows":null},{"label":"Thinness 5-9 years","value":"s","type":"number","required":true,"rows":null},{"label":"Income composition of resources","value":"t","type":"number","required":true,"rows":null},{"label":"Schooling","value":"u","type":"number","required":true,"rows":null}],"formValue":{"a":"","b":"","c":"","d":"","e":"","f":"","g":"","h":"","i":"","j":"","k":"","l":"","m":"","n":"","o":"","p":"","q":"","r":"","s":"","t":"","u":""},"payload":"","submit":"Predict","cancel":"Cancel","topic":"","x":90,"y":340,"wires":[["169cce12.669d62"]]},{"id":"169cce12.669d62","type":"function","z":"c48e06ca.853d48","name":"pre token","func":"global.set(\"a\",msg.payload.a);\nglobal.set(\"b\",msg.payload.b);\nglobal.set(\"c\",msg.payload.c);\nglobal.set(\"d\",msg.payload.d);\nglobal.set(\"e\",msg.payload.e);\nglobal.set(\"f\",msg.payload.f);\nglobal.set(\"g\",msg.payload.g);\nglobal.set(\"h\",msg.payload.h);\nglobal.set(\"i\",msg.payload.i);\nglobal.set(\"j\",msg.payload.j);\nglobal.set(\"k\",msg.payload.k);\nglobal.set(\"l\",msg.payload.l);\nglobal.set(\"m\",msg.payload.m);\nglobal.set(\"n\",msg.payload.n);\nglobal.set(\"o\",msg.payload.o);\nglobal.set(\"p\",msg.payload.p);\nglobal.set(\"q\",msg.payload.q);\nglobal.set(\"r\",msg.payload.r);\nglobal.set(\"s\",msg.payload.s);\nglobal.set(\"t\",msg.payload.t);\nglobal.set(\"u\",msg.payload.u);\n\nvar apikey = \"YxYRBZZTnZuuF41FON3eWHTv2lFQfbEOgwLQ4N9rRK6d\";\nmsg.headers = {\"content-type\":\"application/x-www-form-urlencoded\"};\nmsg.payload = {\"grant_type\":\"urn:ibm:params:oauth:grant-type:apikey\",\"apikey\":apikey};\n\nreturn msg;","outputs":1,"noerr":0,"x":180,"y":220,"wires":[["fee95a72.e00db8"]]},{"id":"fee95a72.e00db8","type":"http request","z":"c48e06ca.853d48","name":"","method":"POST","ret":"obj","paytoqs":false,"url":"https://iam.cloud.ibm.com/identity/token","tls":"","persist":false,"proxy":"","authType":"","x":310,"y":120,"wires":[["dee9c793.efdae8"]]},{"id":"e9e7f403.3a40c8","type":"debug","z":"c48e06ca.853d48","name":"","active":true,"tosidebar":true,"console":false,"tostatus":false,"complete":"payload","targetType":"msg","x":610,"y":400,"wires":[]},{"id":"dee9c793.efdae8","type":"function","z":"c48e06ca.853d48","name":"pre prediction","func":"var token = msg.payload.access_token;\nvar instance_id = \"abea31c3-3ac1-467d-bfe6-a58059bf3209\";\nmsg.headers = {\"Content-Type\": \"application/json\",\"Authorization\":\"Bearer \"+token,\"ML-Instance-ID\":instance_id};\n\nvar a = global.get(\"a\");\nvar b = global.get(\"b\");\nvar c = global.get(\"c\");\nvar d = global.get(\"d\");\nvar e = global.get(\"e\");\nvar f = global.get(\"f\");\nvar g = global.get(\"g\");\nvar h = global.get(\"h\");\nvar i = global.get(\"i\");\nvar j = global.get(\"j\");\nvar k = global.get(\"k\");\nvar l = global.get(\"l\");\nvar m = global.get(\"m\");\nvar n = global.get(\"n\");\nvar o = global.get(\"o\");\nvar p = global.get(\"p\");\nvar q = global.get(\"q\");\nvar r = global.get(\"r\");\nvar s = global.get(\"s\");\nvar t = global.get(\"t\");\nvar u = global.get(\"u\");\n\nmsg.payload = {\"input_data\": [{\"fields\": [\"Country\", \"Year\", \"Status\", \"Adult Mortality\", \"Infant deaths\", \"Alcohol\", \"Percentage expenditure\", \"Hepatitis B\", \"Measles\", \"BMI\", \"Under-five deaths\", \"Polio\", \"Total expenditure\", \"Diphtheria\", \"HIV/AIDS\", \"GDP\", \"Population\", \"Thinness 1-19 years\", \"Thinness 5-9 years\", \"Income composition of resources\", \"Schooling\"], \"values\": [[a,b,c,d,e,f,g,h,i,j,k,l,m,n,o,p,q,r,s,t,u]]}]};\n\nreturn msg;","outputs":1,"noerr":0,"x":320,"y":400,"wires":[["4be86efa.80a54"]]},{"id":"4be86efa.80a54","type":"http request","z":"c48e06ca.853d48","name":"","method":"POST","ret":"obj","paytoqs":false,"url":"https://eu-gb.ml.cloud.ibm.com/v4/deployments/c31845f4-014f-43ef-8fba-faca0ba48172/predictions","tls":"","persist":false,"proxy":"","authType":"","x":470,"y":240,"wires":[["e9e7f403.3a40c8","c4e7b4a4.07c6f8"]]},{"id":"c4e7b4a4.07c6f8","type":"function","z":"c48e06ca.853d48","name":"retrieving prediction","func":"msg.payload = msg.payload.predictions[0].values[0][0];\nreturn msg;","outputs":1,"noerr":0,"x":610,"y":120,"wires":[["6c8941c7.a12f1"]]},{"id":"6c8941c7.a12f1","type":"ui_text","z":"c48e06ca.853d48","group":"bcbbe35.c34962","order":2,"width":0,"height":0,"name":"prediction","label":"Life Expectancy Prediction: ","format":"{{msg.payload}}","layout":"row-spread","x":760,"y":240,"wires":[]}]